setup.py
neuroelectro/__init__.py
neuroelectro/local_settings.py
neuroelectro/manage.py
neuroelectro/models.py
neuroelectro/settings.py
neuroelectro/tests.py
neuroelectro.egg-info/PKG-INFO
neuroelectro.egg-info/SOURCES.txt
neuroelectro.egg-info/dependency_links.txt
neuroelectro.egg-info/entry_points.txt
neuroelectro.egg-info/requires.txt
neuroelectro.egg-info/top_level.txt
neuroelectro/db_functions/__init__.py
neuroelectro/db_functions/countries.py