Metadata-Version: 1.0
Name: neuroelectro
Version: 0.0.2.2
Summary: Electrophysiological information from diverse neuron types
Home-page: http://github.com/neuroelectro/neuroelectro_org
Author: Rick Gerkin
Author-email: rgerkin@asu.edu
License: GPL2
Platform: UNKNOWN
